<?xml version="1.0" encoding="UTF-8"?><record_update table="sp_instance_carousel">
    <sp_instance_carousel action="DELETE">
        <active>true</active>
        <class_name/>
        <color>default</color>
        <css/>
        <glyph/>
        <id>EatMenuCarousel</id>
        <interval>5000</interval>
        <order>1</order>
        <roles/>
        <short_description/>
        <size>md</size>
        <sp_column display_value="1">503701bc97ffe51080e3fef3a253afa0</sp_column>
        <sp_widget display_value="Carousel">cf1a5153cb21020000f8d856634c9c3c</sp_widget>
        <sys_class_name>sp_instance_carousel</sys_class_name>
        <sys_created_by>shey.delacruz</sys_created_by>
        <sys_created_on>2023-06-30 11:07:21</sys_created_on>
        <sys_id>893701bc97ffe51080e3fef3a253affb</sys_id>
        <sys_mod_count>1</sys_mod_count>
        <sys_name/>
        <sys_package display_value="Eat your Heart Out " source="x_1083337_eat">b012b03f9723251080e3fef3a253afb1</sys_package>
        <sys_policy/>
        <sys_scope display_value="Eat your Heart Out ">b012b03f9723251080e3fef3a253afb1</sys_scope>
        <sys_update_name>sp_instance_carousel_893701bc97ffe51080e3fef3a253affb</sys_update_name>
        <sys_updated_by>shey.delacruz</sys_updated_by>
        <sys_updated_on>2023-06-30 11:38:13</sys_updated_on>
        <title/>
        <url/>
        <widget_parameters/>
    </sp_instance_carousel>
    <sys_translated_text action="DELETE" query="documentkey=893701bc97ffe51080e3fef3a253affb"/>
    <sys_update_version action="INSERT_OR_UPDATE">
        <action>DELETE</action>
        <application display_value="Eat your Heart Out ">b012b03f9723251080e3fef3a253afb1</application>
        <file_path/>
        <instance_id>76bde7d3db3fa7449df22f17d4961900</instance_id>
        <instance_name>dev73677</instance_name>
        <name>sp_instance_carousel_893701bc97ffe51080e3fef3a253affb</name>
        <payload><![CDATA[<?xml version="1.0" encoding="UTF-8"?><record_update table="sp_instance_carousel"><sp_instance_carousel action="INSERT_OR_UPDATE"><active>true</active><class_name/><color>default</color><css/><glyph/><id>EatMenuCarousel</id><interval>5000</interval><order>1</order><roles/><short_description/><size>md</size><sp_column display_value="1">503701bc97ffe51080e3fef3a253afa0</sp_column><sp_widget display_value="Carousel">cf1a5153cb21020000f8d856634c9c3c</sp_widget><sys_class_name>sp_instance_carousel</sys_class_name><sys_created_by>shey.delacruz</sys_created_by><sys_created_on>2023-06-30 11:07:21</sys_created_on><sys_id>893701bc97ffe51080e3fef3a253affb</sys_id><sys_mod_count>1</sys_mod_count><sys_name/><sys_package display_value="Eat your Heart Out " source="x_1083337_eat">b012b03f9723251080e3fef3a253afb1</sys_package><sys_policy/><sys_scope display_value="Eat your Heart Out ">b012b03f9723251080e3fef3a253afb1</sys_scope><sys_update_name>sp_instance_carousel_893701bc97ffe51080e3fef3a253affb</sys_update_name><sys_updated_by>shey.delacruz</sys_updated_by><sys_updated_on>2023-06-30 11:38:13</sys_updated_on><title/><url/><widget_parameters/></sp_instance_carousel><sys_translated_text action="delete_multiple" query="documentkey=893701bc97ffe51080e3fef3a253affb"/></record_update>]]></payload>
        <payload_hash>939414911</payload_hash>
        <record_name/>
        <reverted_from/>
        <source>6b53cd509733a51080e3fef3a253aff6</source>
        <source_table>sys_update_set</source_table>
        <state>previous</state>
        <sys_created_by>shey.delacruz</sys_created_by>
        <sys_created_on>2023-06-30 11:38:13</sys_created_on>
        <sys_id>454e0d349733291080e3fef3a253af3d</sys_id>
        <sys_mod_count>0</sys_mod_count>
        <sys_recorded_at>1890c18b7ae0000001</sys_recorded_at>
        <sys_updated_by>shey.delacruz</sys_updated_by>
        <sys_updated_on>2023-06-30 11:38:13</sys_updated_on>
        <type>Instance of Carousel</type>
        <update_guid>0d4e0d34873329107021d75388d7eb3c</update_guid>
        <update_guid_history>0d4e0d34873329107021d75388d7eb3c:939414911,453701bc4affe510ec57a62ad311adfd:1066244913</update_guid_history>
    </sys_update_version>
    <sys_metadata_delete action="INSERT_OR_UPDATE">
        <sys_audit_delete display_value="">5a0f89749733291080e3fef3a253af4e</sys_audit_delete>
        <sys_class_name>sys_metadata_delete</sys_class_name>
        <sys_created_by>shey.delacruz</sys_created_by>
        <sys_created_on>2023-06-30 11:41:34</sys_created_on>
        <sys_db_object display_value="" name="sp_instance_carousel">sp_instance_carousel</sys_db_object>
        <sys_id>06e357d953034438820f0f1db2dc6961</sys_id>
        <sys_metadata>893701bc97ffe51080e3fef3a253affb</sys_metadata>
        <sys_mod_count>0</sys_mod_count>
        <sys_name/>
        <sys_package display_value="Eat your Heart Out " source="x_1083337_eat">b012b03f9723251080e3fef3a253afb1</sys_package>
        <sys_parent/>
        <sys_policy/>
        <sys_scope display_value="Eat your Heart Out ">b012b03f9723251080e3fef3a253afb1</sys_scope>
        <sys_scope_delete display_value="">a40e0342bd8c42a49fd79255a4ecb384</sys_scope_delete>
        <sys_update_name>sp_instance_carousel_893701bc97ffe51080e3fef3a253affb</sys_update_name>
        <sys_update_version display_value="sp_instance_carousel_893701bc97ffe51080e3fef3a253affb">454e0d349733291080e3fef3a253af3d</sys_update_version>
        <sys_updated_by>shey.delacruz</sys_updated_by>
        <sys_updated_on>2023-06-30 11:41:34</sys_updated_on>
    </sys_metadata_delete>
</record_update>
